{
    "title": {
        "en": "The salinity changed",
        "de": "Der Salzgehalt hat sich geändert",
        "fr": "La salinité a changé",
        "it": "La salinità è cambiata",
        "nl": "Het zoutgehalte is veranderd"
    },
    "tokens": [
        {
            "name": "measure_salt",
            "title": {
                "en": "Salinity",
                "de": "Salzgehalt",
                "fr": "Salinité",
                "it": "Salinità",
                "nl": "Zoutgehalte"
            },
            "type": "number",
            "example": 40
        }
    ]
}
